django_settings_toml
