Metadata-Version: 2.1
Name: django-settings-toml
Version: 0.0.4
Summary: Django settings using TOML configuration files.
Home-page: UNKNOWN
Author: Abhilash Raj
Author-email: maxking@asynchronous.in
License: Apache 2.0
Platform: UNKNOWN
Classifier: Intended Audience :: Developers
Classifier: Programming Language :: Python :: 3
Classifier: License :: OSI Approved :: Apache Software License
